reda/__init__.py
reda/configs/__init__.py
reda/configs/configManager.py
reda/containers/BaseContainer.py
reda/containers/CR.py
reda/containers/ERT.py
reda/containers/SIP.py
reda/containers/TDIP.py
reda/containers/__init__.py
reda/containers/sEIT.py
reda/eis/__init__.py
reda/eis/convert.py
reda/eis/plots.py
reda/eis/test_convert.py
reda/eis/units.py
reda/exporters/__init__.py
reda/exporters/bert.py
reda/exporters/crtomo.py
reda/exporters/syscal.py
reda/importers/__init__.py
reda/importers/bert.py
reda/importers/crtomo.py
reda/importers/eit_fzj.py
reda/importers/eit_version_2010.py
reda/importers/eit_version_2013.py
reda/importers/eit_version_2017.py
reda/importers/eit_version_2018a.py
reda/importers/eit_version_20200609.py
reda/importers/geotom.py
reda/importers/iris_syscal_pro.py
reda/importers/mpt_das1.py
reda/importers/radic_sip256c.py
reda/importers/res2dinv.py
reda/importers/sip04.py
reda/importers/legacy/__init__.py
reda/importers/legacy/eit160.py
reda/importers/legacy/eit40.py
reda/importers/utils/__init__.py
reda/importers/utils/decorators.py
reda/importers/utils/transforms.py
reda/main/__init__.py
reda/main/logger.py
reda/main/units.py
reda/plotters/__init__.py
reda/plotters/histograms.py
reda/plotters/plots2d.py
reda/plotters/pseudoplots.py
reda/plotters/time_series.py
reda/tdip/__init__.py
reda/tdip/decay_curve.py
reda/testing/__init__.py
reda/testing/containers.py
reda/testing/test_container_ert.py
reda/testing/test_container_seit.py
reda/testing/data/seit_test_data.zip
reda/testing/ert_container/__init__.py
reda/testing/ert_container/test_K_computation.py
reda/utils/__init__.py
reda/utils/data.py
reda/utils/decorators_and_managers.py
reda/utils/eit_fzj_utils.py
reda/utils/enter_directory.py
reda/utils/filter_config_types.py
reda/utils/fix_sign_with_K.py
reda/utils/geom_fac_crtomo.py
reda/utils/geometric_factors.py
reda/utils/helper_functions.py
reda/utils/mpl.py
reda/utils/norrec.py
reda/utils/pseudo_positions.py
reda-0.1.5.dist-info/COPYING
reda-0.1.5.dist-info/METADATA
reda-0.1.5.dist-info/WHEEL
reda-0.1.5.dist-info/top_level.txt
reda-0.1.5.dist-info/RECORD
