Metadata-Version: 2.1
Name: reda
Version: 0.1.5
Summary: Reproducible Electrical Data Analysis
Home-page: https://github.com/geophysics-ubonn/reda
Author: Maximilian Weigand and Florian M. Wagner
Author-email: mweigand@geo.uni-bonn.de, wagner@geo.uni-bonn.de
License: MIT
Platform: UNKNOWN
Classifier: Programming Language :: Python :: 3
Classifier: License :: OSI Approved :: MIT License
Classifier: Operating System :: OS Independent
Requires-Dist: numpy
Requires-Dist: scipy
Requires-Dist: pandas
Requires-Dist: matplotlib
